ropts/__init__.py
ropts/_modidx.py
ropts/core.py
ropts-0.0.4.dist-info/LICENSE
ropts-0.0.4.dist-info/METADATA
ropts-0.0.4.dist-info/WHEEL
ropts-0.0.4.dist-info/entry_points.txt
ropts-0.0.4.dist-info/top_level.txt
ropts-0.0.4.dist-info/RECORD
