Metadata-Version: 2.1
Name: ropts
Version: 0.0.4
Summary: ropts
Home-page: https://github.com/dsm-72/ropts
Author: dsm-72
Author-email: sumner.magruder@yale.edu
License: Apache Software License 2.0
Keywords: nbdev jupyter notebook python options opts rank choice ranked ropts attr prep attributes preparation data science
Classifier: Development Status :: 4 - Beta
Classifier: Intended Audience :: Developers
Classifier: Natural Language :: English
Classifier: Programming Language :: Python :: 3.11
Classifier: License :: OSI Approved :: Apache Software License
Requires-Python: >=3.11
License-File: LICENSE
Requires-Dist: quac
Requires-Dist: chck
Provides-Extra: dev
